[
  {
    "id": "1",
    "name": "Documents",
    "type": "folder",
    "children": [
      {
        "id": "2",
        "name": "Reports",
        "type": "folder",
        "children": [
          {
            "id": "3",
            "name": "Annual Report.txt",
            "type": "file",
            "content": "Annual report content goes here."
          },
          {
            "id": "4",
            "name": "Summary.pdf",
            "type": "file",
            "content": "PDF content cannot be previewed."
          }
        ]
      },
      {
        "id": "5",
        "name": "Meeting Notes",
        "type": "folder",
        "children": [
          {
            "id": "6",
            "name": "Notes.txt",
            "type": "file",
            "content": "Meeting notes from January."
          }
        ]
      }
    ]
  },
  {
    "id": "7",
    "name": "Images",
    "type": "folder",
    "children": [
      {
        "id": "8",
        "name": "Vacation",
        "type": "folder",
        "children": [
          {
            "id": "9",
            "name": "beach.png",
            "type": "file",
            "content": "data:image/png;base64,..."
          },
          {
            "id": "10",
            "name": "mountains.png",
            "type": "file",
            "content": "data:image/png;base64,..."
          }
        ]
      },
      {
        "id": "11",
        "name": "Icons",
        "type": "folder",
        "children": [
          {
            "id": "12",
            "name": "logo.svg",
            "type": "file",
            "content": "<svg>...</svg>"
          }
        ]
      }
    ]
  }
]
